dreams/__init__.py
dreams/sites/__init__.py
dreams/sites/noodlemagazine/__init__.py
dreams/sites/noodlemagazine/embed.py
dreams/sites/noodlemagazine/search_porn.py
dreams/sites/noodlemagazine/utils.py
dreams/sites/only/__init__.py
dreams/sites/only/nudes7/__init__.py
dreams/sites/only/nudes7/nudes7.py
dreams/sites/only/viralpornhub/__init__.py
dreams/sites/only/viralpornhub/viralpornhub.py
dreams/sites/pornhub/__init__.py
dreams/sites/pornhub/embed.py
dreams/sites/pornhub/search_porn.py
dreams/sites/pornhub/utils.py
dreams/sites/pornone/__init__.py
dreams/sites/pornone/pornone.py
dreams/sites/spankbang/__init__.py
dreams/sites/spankbang/embed.py
dreams/sites/spankbang/schoolbag.py
dreams/sites/spankbang/search_porn.py
dreams/sites/spankbang/spankbang.py
dreams/sites/tnaflix/__init__.py
dreams/sites/tnaflix/embed.py
dreams/sites/tnaflix/search_porn.py
dreams/sites/ukdevilz/__init__.py
dreams/sites/ukdevilz/ukdevilz.py
dreams/sites/xvideos/__init__.py
dreams/sites/xvideos/embed.py
dreams/sites/xvideos/search_porn.py
dreams/sites/xvideos/utils.py
dreams/utils/__init__.py
dreams/utils/objects.py
dreams/utils/settings.py
tests/__init__.py
tests/test_uk.py
tests/test_get_video_embed/__init__.py
tests/test_get_video_embed/test_nd.py
tests/test_get_video_embed/test_ph.py
tests/test_get_video_embed/test_sb.py
tests/test_get_video_embed/test_tn.py
tests/test_search_porn/__init__.py
tests/test_search_porn/test_nd.py
tests/test_search_porn/test_ph.py
tests/test_search_porn/test_pn.py
tests/test_search_porn/test_sb.py
tests/test_search_porn/test_tn.py
tests/test_search_porn/test_uk.py
tests/test_search_porn/test_unit_nudes7.py
tests/test_search_porn/test_unit_viralpornhub.py
tests/test_search_porn/test_xv.py
dreams-0.3.9.2.dist-info/LICENSE
dreams-0.3.9.2.dist-info/METADATA
dreams-0.3.9.2.dist-info/WHEEL
dreams-0.3.9.2.dist-info/top_level.txt
dreams-0.3.9.2.dist-info/RECORD
