Metadata-Version: 2.1
Name: dreams
Version: 0.3.9.2
Summary: Library for getting educative url video's
Home-page: https://github.com/reinanbr/dreams
Author: Reinan Br
Author-email: slimchatuba@gmail.com
License: BSD v3
Keywords: video link api porn
License-File: LICENSE
Requires-Dist: requests
Requires-Dist: mechanicalsoup
Requires-Dist: bs4
Requires-Dist: requests-html
Requires-Dist: kitano
